topsis/__init__.py
topsis/algo.py
topsis/main.py
topsis_Karan_102217128-0.0.4.dist-info/LICENSE
topsis_Karan_102217128-0.0.4.dist-info/METADATA
topsis_Karan_102217128-0.0.4.dist-info/WHEEL
topsis_Karan_102217128-0.0.4.dist-info/top_level.txt
topsis_Karan_102217128-0.0.4.dist-info/RECORD
