Metadata-Version: 2.1
Name: topsis-Karan-102217128
Version: 0.0.4
Author: Karanjot Singh
Author-email: ksingh11_be22@thapar.edu
License: MIT
License-File: LICENSE
Requires-Dist: pandas
Requires-Dist: numpy
